MANIFEST.in
README.rst
setup.py
dipc/__init__.py
dipc/decorators.py
dipc/lock.py
dipc/semaphore.py
dipc.egg-info/PKG-INFO
dipc.egg-info/SOURCES.txt
dipc.egg-info/dependency_links.txt
dipc.egg-info/requires.txt
dipc.egg-info/top_level.txt
dipc.egg-info/zip-safe
tests/__init__.py
tests/test_lock.py
tests/test_semaphore.py