Metadata-Version: 1.1
Name: dipc
Version: 0.4
Summary: Distributed Inter-Process Communication Library implemented in Python and Memcache server
Home-page: https://github.com/loucash/dipc
Author: Lukasz Biedrycki
Author-email: lukasz.biedrycki@gmail.com
License: New BSD License
Keywords: distributed ipc python memcache lock semaphore inter process communication
Platform: UNKNOWN
Classifier: Development Status :: 4 - Beta
Classifier: Environment :: Other Environment
Classifier: Environment :: Web Environment
Classifier: Intended Audience :: Developers
Classifier: License :: OSI Approved :: BSD License
Classifier: Operating System :: OS Independent
Classifier: Programming Language :: Python
Classifier: Topic :: Utilities
Classifier: Topic :: Software Development :: Libraries :: Python Modules
Requires: python_memcached
